Workbook

Sheet 1. Resumen Ejecutivo
A1: SkillRoute vs The World — Matriz Comparativa Maestra
A2: Análisis competitivo internacional · Generado 2026-04-25 · Estrategia International-Grade
A4: Tabla 1 · Plataformas analizadas
A5: Plataforma | B5: Origen | C5: Pricing estimado | D5: Funding / Backing | E5: Cobertura
A6: Optibus | B6: Israel/UK | C6: $$$$ $30-800K/año | D6: $140M Series D | E6: 6.000 ciudades, 35 países
A7: Swiftly | B7: USA | C7: $$$ $25-600K/año | D7: $50M Series C | E7: 136 agencies, 8 países
A8: Remix | B8: USA (Via Group) | C8: $$ $15-200K/año | D8: Adquirida Via $100M | E8: 340 cities, 22 países
A9: Trapeze | B9: Canadá (Modaxo/Constellation) | C9: $$$$$ $50K-5M/año | D9: Constellation Software | E9: Enterprise USA/Canadá + Brasil
A10: SkillRoute | B10: Uruguay | C10: $ tier por buses (a definir) | D10: Bootstrap | E10: 4 operadores Montevideo
A13: Tabla 2 · Score consolidado por categoría (suma 0-5 por función)
A14: Categoría | B14: Optibus | C14: Swiftly | D14: Remix | E14: Trapeze | F14: SkillRoute hoy | G14: SkillRoute target
A15: Planning | B15: =SUMIF('2. Matriz Funciones'!A:A,"Planning",'2. Matriz Funciones'!C:C) -> 14 | C15: =SUMIF('2. Matriz Funciones'!A:A,"Planning",'2. Matriz Funciones'!D:D) -> 1 | D15: =SUMIF('2. Matriz Funciones'!A:A,"Planning",'2. Matriz Funciones'!E:E) -> 29 | E15: =SUMIF('2. Matriz Funciones'!A:A,"Planning",'2. Matriz Funciones'!F:F) -> 14 | F15: =SUMIF('2. Matriz Funciones'!A:A,"Planning",'2. Matriz Funciones'!G:G) -> 5 | G15: =SUMIF('2. Matriz Funciones'!A:A,"Planning",'2. Matriz Funciones'!H:H) -> 21
A16: Scheduling | B16: =SUMIF('2. Matriz Funciones'!A:A,"Scheduling",'2. Matriz Funciones'!C:C) -> 19 | C16: =SUMIF('2. Matriz Funciones'!A:A,"Scheduling",'2. Matriz Funciones'!D:D) -> 0 | D16: =SUMIF('2. Matriz Funciones'!A:A,"Scheduling",'2. Matriz Funciones'!E:E) -> 8 | E16: =SUMIF('2. Matriz Funciones'!A:A,"Scheduling",'2. Matriz Funciones'!F:F) -> 11 | F16: =SUMIF('2. Matriz Funciones'!A:A,"Scheduling",'2. Matriz Funciones'!G:G) -> 8 | G16: =SUMIF('2. Matriz Funciones'!A:A,"Scheduling",'2. Matriz Funciones'!H:H) -> 16
A17: Real-time | B17: =SUMIF('2. Matriz Funciones'!A:A,"Real-time",'2. Matriz Funciones'!C:C) -> 28 | C17: =SUMIF('2. Matriz Funciones'!A:A,"Real-time",'2. Matriz Funciones'!D:D) -> 39 | D17: =SUMIF('2. Matriz Funciones'!A:A,"Real-time",'2. Matriz Funciones'!E:E) -> 2 | E17: =SUMIF('2. Matriz Funciones'!A:A,"Real-time",'2. Matriz Funciones'!F:F) -> 28 | F17: =SUMIF('2. Matriz Funciones'!A:A,"Real-time",'2. Matriz Funciones'!G:G) -> 18 | G17: =SUMIF('2. Matriz Funciones'!A:A,"Real-time",'2. Matriz Funciones'!H:H) -> 36
A18: Analytics | B18: =SUMIF('2. Matriz Funciones'!A:A,"Analytics",'2. Matriz Funciones'!C:C) -> 22 | C18: =SUMIF('2. Matriz Funciones'!A:A,"Analytics",'2. Matriz Funciones'!D:D) -> 30 | D18: =SUMIF('2. Matriz Funciones'!A:A,"Analytics",'2. Matriz Funciones'!E:E) -> 3 | E18: =SUMIF('2. Matriz Funciones'!A:A,"Analytics",'2. Matriz Funciones'!F:F) -> 19 | F18: =SUMIF('2. Matriz Funciones'!A:A,"Analytics",'2. Matriz Funciones'!G:G) -> 15 | G18: =SUMIF('2. Matriz Funciones'!A:A,"Analytics",'2. Matriz Funciones'!H:H) -> 26
A19: EAM | B19: =SUMIF('2. Matriz Funciones'!A:A,"EAM",'2. Matriz Funciones'!C:C) -> 10 | C19: =SUMIF('2. Matriz Funciones'!A:A,"EAM",'2. Matriz Funciones'!D:D) -> 0 | D19: =SUMIF('2. Matriz Funciones'!A:A,"EAM",'2. Matriz Funciones'!E:E) -> 0 | E19: =SUMIF('2. Matriz Funciones'!A:A,"EAM",'2. Matriz Funciones'!F:F) -> 21 | F19: =SUMIF('2. Matriz Funciones'!A:A,"EAM",'2. Matriz Funciones'!G:G) -> 7 | G19: =SUMIF('2. Matriz Funciones'!A:A,"EAM",'2. Matriz Funciones'!H:H) -> 19
A20: Cross-op ⭐ | B20: =SUMIF('2. Matriz Funciones'!A:A,"Cross-op ⭐",'2. Matriz Funciones'!C:C) -> 1 | C20: =SUMIF('2. Matriz Funciones'!A:A,"Cross-op ⭐",'2. Matriz Funciones'!D:D) -> 1 | D20: =SUMIF('2. Matriz Funciones'!A:A,"Cross-op ⭐",'2. Matriz Funciones'!E:E) -> 1 | E20: =SUMIF('2. Matriz Funciones'!A:A,"Cross-op ⭐",'2. Matriz Funciones'!F:F) -> 1 | F20: =SUMIF('2. Matriz Funciones'!A:A,"Cross-op ⭐",'2. Matriz Funciones'!G:G) -> 22 | G20: =SUMIF('2. Matriz Funciones'!A:A,"Cross-op ⭐",'2. Matriz Funciones'!H:H) -> 25
A21: Passenger | B21: =SUMIF('2. Matriz Funciones'!A:A,"Passenger",'2. Matriz Funciones'!C:C) -> 10 | C21: =SUMIF('2. Matriz Funciones'!A:A,"Passenger",'2. Matriz Funciones'!D:D) -> 8 | D21: =SUMIF('2. Matriz Funciones'!A:A,"Passenger",'2. Matriz Funciones'!E:E) -> 2 | E21: =SUMIF('2. Matriz Funciones'!A:A,"Passenger",'2. Matriz Funciones'!F:F) -> 10 | F21: =SUMIF('2. Matriz Funciones'!A:A,"Passenger",'2. Matriz Funciones'!G:G) -> 4 | G21: =SUMIF('2. Matriz Funciones'!A:A,"Passenger",'2. Matriz Funciones'!H:H) -> 9
A22: Standards | B22: =SUMIF('2. Matriz Funciones'!A:A,"Standards",'2. Matriz Funciones'!C:C) -> 20 | C22: =SUMIF('2. Matriz Funciones'!A:A,"Standards",'2. Matriz Funciones'!D:D) -> 13 | D22: =SUMIF('2. Matriz Funciones'!A:A,"Standards",'2. Matriz Funciones'!E:E) -> 10 | E22: =SUMIF('2. Matriz Funciones'!A:A,"Standards",'2. Matriz Funciones'!F:F) -> 17 | F22: =SUMIF('2. Matriz Funciones'!A:A,"Standards",'2. Matriz Funciones'!G:G) -> 13 | G22: =SUMIF('2. Matriz Funciones'!A:A,"Standards",'2. Matriz Funciones'!H:H) -> 24
A23: Comercial | B23: =SUMIF('2. Matriz Funciones'!A:A,"Comercial",'2. Matriz Funciones'!C:C) -> 11 | C23: =SUMIF('2. Matriz Funciones'!A:A,"Comercial",'2. Matriz Funciones'!D:D) -> 11 | D23: =SUMIF('2. Matriz Funciones'!A:A,"Comercial",'2. Matriz Funciones'!E:E) -> 13 | E23: =SUMIF('2. Matriz Funciones'!A:A,"Comercial",'2. Matriz Funciones'!F:F) -> 7 | F23: =SUMIF('2. Matriz Funciones'!A:A,"Comercial",'2. Matriz Funciones'!G:G) -> 20 | G23: =SUMIF('2. Matriz Funciones'!A:A,"Comercial",'2. Matriz Funciones'!H:H) -> 24
A24: Regulatorio ⭐ | B24: =SUMIF('2. Matriz Funciones'!A:A,"Regulatorio ⭐",'2. Matriz Funciones'!C:C) -> 1 | C24: =SUMIF('2. Matriz Funciones'!A:A,"Regulatorio ⭐",'2. Matriz Funciones'!D:D) -> 0 | D24: =SUMIF('2. Matriz Funciones'!A:A,"Regulatorio ⭐",'2. Matriz Funciones'!E:E) -> 1 | E24: =SUMIF('2. Matriz Funciones'!A:A,"Regulatorio ⭐",'2. Matriz Funciones'!F:F) -> 2 | F24: =SUMIF('2. Matriz Funciones'!A:A,"Regulatorio ⭐",'2. Matriz Funciones'!G:G) -> 5 | G24: =SUMIF('2. Matriz Funciones'!A:A,"Regulatorio ⭐",'2. Matriz Funciones'!H:H) -> 14
A25: TOTAL | B25: =SUM(B15:B24) -> 136 | C25: =SUM(C15:C24) -> 103 | D25: =SUM(D15:D24) -> 69 | E25: =SUM(E15:E24) -> 130 | F25: =SUM(F15:F24) -> 117 | G25: =SUM(G15:G24) -> 214
A27: INTERPRETACIÓN
A28: • Score por función: 0=no tiene · 1=básico · 2=funcional · 3=bueno · 4=excelente · 5=mejor del mundo
A29: • Categorías marcadas ⭐ son nuestros diferenciadores estructurales (cross-op, regulatorio).
A30: • 'SkillRoute hoy' = estado real abril 2026 · 'SkillRoute target' = post roadmap de cierre de gaps.
A31: • Cuando el target supera al líder en su propia categoría = ventaja competitiva proyectada.
A32: • Cuando el hoy ya supera a los 4 líderes (cross-op, regulatorio) = moat estructural, defender.

Sheet 2. Matriz Funciones
A1: Categoría | B1: Función | C1: Optibus | D1: Swiftly | E1: Remix | F1: Trapeze | G1: SkillRoute hoy | H1: SkillRoute target | I1: Prioridad | J1: Esfuerzo | K1: Notas / Acción
A2: Planning | B2: Network editor visual (drag-drop líneas/paradas) | C2: 3 | D2: 0 | E2: 5 | F2: 3 | G2: 1 | H2: 4 | I2: Alta | J2: Alto | K2: Remix es referencia. Crear NetworkEditor.tsx
A3: Planning | B3: Demographic data overlay por barrio | C3: 1 | D3: 0 | E3: 5 | F3: 1 | G3: 0 | H3: 4 | I3: Alta | J3: Medio | K3: Integrar INE Uruguay + IMM datos abiertos
A4: Planning | B4: Equity analysis (Title VI USA / Latam) | C4: 1 | D4: 0 | E4: 5 | F4: 1 | G4: 0 | H4: 5 | I4: Alta | J4: Alto | K4: Diferenciador estratégico Latam. Adaptado a Ley 18.331
A5: Planning | B5: Visualización impacto financiero al editar | C5: 4 | D5: 0 | E5: 5 | F5: 3 | G5: 1 | H5: 4 | I5: Media | J5: Medio | K5: Conectar forecastService al editor
A6: Planning | B6: GTFS import/edit/export visual | C6: 4 | D6: 1 | E6: 5 | F6: 4 | G6: 3 | H6: 4 | I6: Media | J6: Medio | K6: Mejorar editor GTFS
A7: Planning | B7: Street design (BRT, ciclovías) | C7: 1 | D7: 0 | E7: 4 | F7: 2 | G7: 0 | H7: 0 | I7: Baja | J7: Alto | K7: Fuera de scope SkillRoute
A8: Scheduling | B8: Schedule optimization AI/ML | C8: 5 | D8: 0 | E8: 3 | F8: 4 | G8: 2 | H8: 4 | I8: Alta | J8: Alto | K8: Integrar OR-Tools (Google) o algoritmos clásicos
A9: Scheduling | B9: Rostering / driver rotation | C9: 4 | D9: 0 | E9: 3 | F9: 4 | G9: 3 | H9: 4 | I9: Media | J9: Medio | K9: Pulir RotationMatrix existente
A10: Scheduling | B10: Driver Relief Scheduling | C10: 5 | D10: 0 | E10: 2 | F10: 3 | G10: 3 | H10: 4 | I10: Media | J10: Medio | K10: Mejorar
A11: Scheduling | B11: GenAI declarativa (Preference Designer) | C11: 5 | D11: 0 | E11: 0 | F11: 0 | G11: 0 | H11: 4 | I11: Alta | J11: Medio | K11: Ventaja: español nativo. Optibus está en inglés
A12: Real-time | B12: Real-time AVL + dispatch | C12: 4 | D12: 5 | E12: 1 | F12: 4 | G12: 4 | H12: 5 | I12: Media | J12: Bajo | K12: LiveMap + FleetMonitor cubren bien
A13: Real-time | B13: Live map / Map Hub unificado | C13: 4 | D13: 5 | E13: 1 | F13: 4 | G13: 3 | H13: 5 | I13: Media | J13: Medio | K13: Unificar LiveMap + CorridorMap + FleetMonitor
... A52: Regulatorio ⭐ | B52: Forecasting ingresos cross-op | C52: 1 | D52: 0 | E52: 0 | F52: 1 | G52: 2 | H52: 4 | I52: Media | J52: Medio | K52: ✅ Diferenciador analítico

Sheet 3. Estándares Internacionales
A1: Mapeo de cumplimiento contra estándares internacionales
A2: Documenta evidencia y gap por estándar aplicable a SkillRoute
A4: Estándar | B4: Categoría | C4: Aplicable a SkillRoute | D4: Estado actual | E4: Evidencia disponible | F4: Gap a cerrar | G4: Prioridad
A5: GTFS-Static | B5: Datos / Interoperabilidad | C5: Sí — fuente única de horarios y rutas estáticos | D5: Implementado parcial | E5: functions/src/gtfsStatic.ts existente | F5: Validar contra spec V2 oficial Google | G5: Alta
A6: GTFS-Realtime V2 | B6: Datos / Interoperabilidad | C6: Sí — VehiclePositions + TripUpdates + Alerts | D6: Implementado | E6: gtfsRealtime.ts con delay real | F6: Auto-publish Service Alerts desde operations | G6: Alta
A7: NeTEx | B7: Datos / Europa | C7: Parcial — solo si entramos a UE | D7: Implementado parcial | E7: netexEndpoint.ts mínimo | F7: Profundizar para mercado UE futuro | G7: Baja
A8: SIRI v2 | B8: Datos / Europa | C8: Parcial — complemento NeTEx | D8: Implementado parcial | E8: siriRealtime.ts mínimo | F8: Idem NeTEx | G8: Baja
A9: TCRP 195 (DRO/Headway) | B9: Métricas / TRB USA | C9: Sí — base académica de ShadowRadar | D9: Implementado y EXTENDIDO cross-op | E9: ShadowRadar DRO+HRR live cross-op | F9: Documentar publicamente la implementación | G9: Alta
A10: TCRP 100 (BRT) | B10: Métricas / TRB USA | C10: Solo si hay BRT en clientes | D10: No aplicable hoy | E10: — | F10: Roadmap futuro si CUTCSA implementa BRT | G10: Baja
A11: UITP best practices | B11: KPIs / Internacional | C11: Sí — KPIs canónicos | D11: Implementado parcial | E11: OTPDashboard, KPI snapshots | F11: Auditoría formal contra UITP framework | G11: Media
A12: EN 13816 | B12: Calidad / Europa | C12: Parcial — calidad de servicio | D12: No implementado | E12: — | F12: Roadmap si entramos a UE | G12: Baja
A13: ISO/IEC 25010 | B13: Software Quality | C13: Sí — quality model 8 ejes | D13: No auditado formalmente | E13: Tests Vitest + Playwright + integrity script | F13: Auditoría formal con consultora | G13: Media
A14: ISO/IEC 27001 | B14: Information Security | C14: Sí — clientes enterprise lo demandan | D14: No certificado | E14: Firestore RBAC + JWT + audit log | F14: Compliance statement primero, certificación 2027 | G14: Alta
A15: SOC 2 Type II | B15: Security/Availability/Confidentiality | C15: Sí — alternativa a ISO 27001 para USA | D15: No certificado | E15: Idem ISO 27001 | F15: Decisión estratégica: ISO 27001 o SOC 2 (no ambas) | G15: Alta
... A21: HIPAA | B21: Salud / USA | C21: No aplicable | D21: — | E21: — | F21: — | G21: —

Sheet 4. Gap Analysis Priorizado
A1: Gap Analysis · ranking por (Impacto × Diferencial) ÷ Esfuerzo
A2: Cierre priorizado de gaps detectados — base para roadmap Fase 3
A4: # | B4: Gap a cerrar | C4: Categoría | D4: Impacto comercial (1-5) | E4: Diferencial competitivo (1-5) | F4: Esfuerzo (1-5) | G4: Score = (I×D)÷E
A5: 1 | B5: HeadwayInsights.tsx (bunching/gapping single-op + HRR cross-op) | C5: Real-time | D5: 5 | E5: 5 | F5: 2 | G5: =ROUND((D5*E5)/F5,2) -> 12.5
A6: 2 | B6: GTFS-RT Service Alerts auto-publish desde operations | C6: Analytics | D6: 4 | E6: 3 | F6: 1 | G6: =ROUND((D6*E6)/F6,2) -> 12
A7: 3 | B7: Pricing público con tier por buses | C7: Comercial | D7: 5 | E7: 5 | F7: 1 | G7: =ROUND((D7*E7)/F7,2) -> 25
A8: 4 | B8: Documentar onboarding 2-4 semanas con evidencia | C8: Comercial | D8: 4 | E8: 5 | F8: 1 | G8: =ROUND((D8*E8)/F8,2) -> 20
A9: 5 | B9: Análisis Equidad Territorial Latam (engine) | C9: Regulatorio ⭐ | D9: 5 | E9: 5 | F9: 4 | G9: =ROUND((D9*E9)/F9,2) -> 6.25
A10: 6 | B10: Predictions ETA modelo ML básico | C10: Real-time | D10: 5 | E10: 3 | F10: 4 | G10: =ROUND((D10*E10)/F10,2) -> 3.75
A11: 7 | B11: NetworkEditor.tsx visual edit de red | C11: Planning | D11: 4 | E11: 3 | F11: 5 | G11: =ROUND((D11*E11)/F11,2) -> 2.4
A12: 8 | B12: Schema EAM completo (work orders, lifecycle, inventory) | C12: EAM | D12: 5 | E12: 2 | F12: 5 | G12: =ROUND((D12*E12)/F12,2) -> 2
A13: 9 | B13: Schedule optimization con OR-Tools | C13: Scheduling | D13: 4 | E13: 3 | F13: 4 | G13: =ROUND((D13*E13)/F13,2) -> 3
A14: 10 | B14: GenAI Preference Designer en español | C14: Scheduling | D14: 4 | E14: 4 | F14: 3 | G14: =ROUND((D14*E14)/F14,2) -> 5.33
A15: 11 | B15: Demographic data overlay (INE Uruguay) | C15: Planning | D15: 4 | E15: 4 | F15: 3 | G15: =ROUND((D15*E15)/F15,2) -> 5.33
A16: 12 | B16: Compliance statement ISO 27001 público | C16: Standards | D16: 5 | E16: 4 | F16: 3 | G16: =ROUND((D16*E16)/F16,2) -> 6.67
... A33: 29 | B33: Inteligencia Cittati (Brasil) — investigación comercial | C33: Comercial | D33: 5 | E33: 4 | F33: 1 | G33: =ROUND((D33*E33)/F33,2) -> 20
A35: ℹ️ Para ordenar por score descendente: seleccionar tabla y Datos → Ordenar → Columna G descendente.

Sheet 5. Diferenciadores SkillRoute
A1: Diferenciadores estructurales únicos de SkillRoute
A2: Capacidades que NINGÚN competidor analizado ofrece — defender y profundizar
A4: # | B4: Diferenciador | C4: Por qué nadie más lo hace | D4: Score actual SkillRoute | E4: Acción para profundizar | F4: Riesgo de ser copiado
A5: 1 | B5: DRO live cross-operador (TCRP 195 implementado en tiempo real con 4 operadores cruzados) | C5: Optibus/Swiftly/Remix/Trapeze son single-tenant. Cada uno vende a UN operador. Mezclar datos de múltiples operadores requeriría rehacer su modelo de negocio. | D5: 5 | E5: Documentar metodología pública. Considerar patente del método. | F5: Bajo — requeriría que un competidor rehaga su modelo de negocio. Tiempo estimado: 2-3 años.
A6: 2 | B6: HRR live cross-op (Headway-to-Rival Ratio) | C6: Métrica académica TCRP que ningún competidor implementa en producto comercial. Requiere datos cross-op. | D6: 4 | E6: Profundizar UI dedicada. Crear módulo HeadwayInsights con HRR como vista premium. | F6: Bajo — misma razón que DRO.
A7: 3 | B7: Cobertura cross-op real-time (cumplimiento OTP de 4 operadores simultáneos sobre mismos corredores) | C7: Requiere datos cross-op. No replicable single-tenant. | D7: 4 | E7: Dashboard ejecutivo de Cobertura con vista para reguladores. | F7: Bajo.
A8: 4 | B8: Análisis de Penetración por corredor (market share por línea × agencia, snapshot diario) | C8: Optibus tiene algo similar pero solo para el operador propio. Nadie hace cross-op. | D8: 4 | E8: Cron diario ya corre. Mejorar UI histórica + comparativa. | F8: Bajo.
A9: 5 | B9: Multi-tenancy nativa de operadores en una plataforma | C9: Los 4 líderes son single-tenant por diseño. Cada cliente tiene sus datos en silo. SkillRoute nació cross-op. | D9: 5 | E9: Defender arquitectura. Cualquier feature nueva debe respetar multi-tenancy. | F9: Bajo — decisión arquitectónica de origen.
A10: 6 | B10: Dossier regulatorio automatizado (output preparado para autoridad reguladora con un click) | C10: Trapeze tiene compliance reports pero no automatizado. Optibus/Swiftly/Remix venden a las agencies, no a reguladores. | D10: 3 | E10: Profundizar formato + integración con IMM/STM/CAF. | F10: Medio — Trapeze podría adaptar.
A11: 7 | B11: Análisis Equidad Territorial Latam (inspirado en Title VI Remix, adaptado a Ley 18.331 Uruguay) | C11: Remix Title VI es US-specific. Nadie lo adaptó a Latam. | D11: 0 | E11: Crear engine. Integrar datos INE Uruguay. Roadmap alto. | F11: Medio — Remix podría adaptar para Latam.
A12: 8 | B12: Idioma español nativo + soporte regional Latam | C12: Optibus/Swiftly/Remix/Trapeze son English-first. Cittati (Trapeze Brasil) es portugués. | D12: 3 | E12: Mantener todo en español. Agregar inglés/portugués después. | F12: Medio — Cittati ya está en Brasil.
A13: 9 | B13: Pricing accesible para operadores 50-500 buses | C13: Los 4 líderes excluyen este segmento por pricing enterprise opaco. | D13: 5 | E13: Definir tiers públicos. Publicar en página comercial. | F13: Bajo — los líderes no van a bajar pricing por nosotros.
A14: 10 | B14: Onboarding rápido (2-4 semanas vs 6-18 meses) | C14: Trapeze 6-18 meses, Optibus similar, Swiftly 1-3 meses, Remix días-semanas. | D14: 5 | E14: Documentar proceso con evidencia. Caso UCOT como referencia. | F14: Medio — Remix ya tiene onboarding rápido, pero foco diferente.
A15: 11 | B15: Forecasting de ingresos cross-op | C15: Modelos forecast existentes son single-operator. | D15: 2 | E15: Profundizar forecastService con cross-op. | F15: Medio.

Sheet 6. Riesgos Estratégicos
A1: Riesgos estratégicos identificados en el análisis competitivo
A3: # | B3: Riesgo | C3: Probabilidad | D3: Impacto | E3: Mitigación
A4: 1 | B4: Modaxo/Constellation Software penetra Latam vía Cittati (Brasil) y llega a CUTCSA antes que nosotros | C4: Alta | D4: Alto | E4: Velocidad. Cerrar relación profunda con CUTCSA + IMM antes de exposición pública. Documentar diferenciadores cross-op antes de que Modaxo los vea.
A5: 2 | B5: Optibus lanza 'Optibus Lite' con pricing agresivo para Latam (tienen $140M de funding) | C5: Media | D5: Alto | E5: Construir el moat cross-op rápido. Patentar métodos clave si es posible. Asegurar onboarding super rápido (irreplicable).
A6: 3 | B6: Swiftly se expande a Latam con piloto en agencia grande (Bogotá, Buenos Aires, Santiago, Lima) | C6: Media | D6: Medio | E6: Penetrar Latam con velocidad. Construir relación con UITP-LATAM para visibilidad institucional.
A7: 4 | B7: Constellation Software intenta adquirir SkillRoute (modelo agregador serial) | C7: Media (si crecemos) | D7: Variable | E7: Decisión estratégica del fundador: ¿abierto a M&A o crecer independiente? Definir tesis. Considerar protección IP.
A8: 5 | B8: Remix + Via TransitTech entran a Latam con suite end-to-end | C8: Media | D8: Medio | E8: Diferenciar en cross-op. Latam tiene necesidades regulatorias distintas a USA.
A9: 6 | B9: Cittati (Brasil) lanza herramientas tipo SkillRoute desde dentro | C9: Media (ya están en mercado) | D9: Alto | E9: Investigar Cittati exhaustivamente. Identificar gaps que ellos no cubren. Penetrar Uruguay/Argentina antes de que se expandan.
A10: 7 | B10: Operador grande (CUTCSA o IMM) decide construir solución in-house | C10: Baja-Media | D10: Alto | E10: Demostrar TCO claramente menor que in-house. Documentar mantenimiento y evolución como costos reales que cualquier in-house enfrenta.
A11: 8 | B11: GTFS-RT V3 cambia estándares y nos obliga a refactor | C11: Baja | D11: Medio | E11: Mantener implementación cerca de spec. Participar en discusiones de Google.
A12: 9 | B12: Cambios regulatorios STM/IMM cambian KPIs requeridos | C12: Media | D12: Medio | E12: Arquitectura modular permite adaptarse. Mantener relación cercana con regulador.
A13: 10 | B13: Falla de seguridad pública (data breach) destruye credibilidad | C13: Baja-Media | D13: Crítico | E13: Compliance ISO 27001 / SOC 2 prioritario. Auditorías periódicas. Bug bounty program.
